decyclify/__init__.py
decyclify/functions.py
decyclify/node_iterators.py
decyclify-0.1.dist-info/LICENSE
decyclify-0.1.dist-info/METADATA
decyclify-0.1.dist-info/WHEEL
decyclify-0.1.dist-info/top_level.txt
decyclify-0.1.dist-info/RECORD
