Metadata-Version: 2.1
Name: decyclify
Version: 0.1
Summary: Graph decyclify algorithm implementation as in Sandnes & Sinnen paper (2004) in Python
Home-page: https://github.com/kinow/decyclify
Author: Bruno P. Kinoshita
Author-email: brunodepaulak@yahoo.com.br
License: Apache License 2.0
Project-URL: Documentation, https://github.com/kinow/decyclify
Project-URL: Source, https://github.com/kinow/decyclify
Project-URL: Tracker, https://github.com/kinow/decyclify/issues
Keywords: algorithms,cyclic,graph,graph-theory
Platform: any
Classifier: Environment :: Console
Classifier: Intended Audience :: Developers
Classifier: Intended Audience :: System Administrators
Classifier: Intended Audience :: Science/Research
Classifier: License :: OSI Approved :: Apache Software License
Classifier: Operating System :: POSIX :: Linux
Classifier: Programming Language :: Python
Classifier: Programming Language :: Python :: 3.7
Classifier: Programming Language :: Python :: 3.8
Classifier: Programming Language :: Python :: Implementation :: CPython
Classifier: Topic :: Scientific/Engineering :: Atmospheric Science
Requires-Dist: networkx (==2.4.*)
Requires-Dist: numpy (==1.19.*)
Requires-Dist: tabulate (==0.8.*)
Provides-Extra: all
Requires-Dist: pytest (==5.4.*) ; extra == 'all'
Requires-Dist: coverage (==5.2.*) ; extra == 'all'
Requires-Dist: pytest-cov (==2.10.*) ; extra == 'all'
